_spock/__init__.py
_spock/exceptions.py
_spock/helper.py
_spock/param_table.py
_spock/parameter.py
_spock/plugin.py
_spock/spock.py
spock/__init__.py
spock/py.typed
pyspock-0.3.0.dist-info/entry_points.txt
pyspock-0.3.0.dist-info/LICENSE
pyspock-0.3.0.dist-info/WHEEL
pyspock-0.3.0.dist-info/METADATA
pyspock-0.3.0.dist-info/RECORD
