Metadata-Version: 2.1
Name: pyspock
Version: 0.3.0
Summary: Python implementation for spock framework
License: MIT
Keywords: test,unittest,spock,bdd
Author: ZhengYu, Xu
Author-email: zen-xu@outlook.com
Requires-Python: >=3.7,<4.0
Classifier: Development Status :: 4 - Beta
Classifier: Framework :: Pytest
Classifier: License :: OSI Approved :: MIT License
Classifier: Operating System :: MacOS :: MacOS X
Classifier: Operating System :: Microsoft :: Windows
Classifier: Operating System :: POSIX
Classifier: Programming Language :: Python :: 3
Classifier: Programming Language :: Python :: 3.7
Classifier: Programming Language :: Python :: 3.8
Classifier: Programming Language :: Python :: 3.9
Classifier: Topic :: Software Development :: Libraries
Classifier: Topic :: Software Development :: Testing
Classifier: Topic :: Software Development :: Testing :: BDD
Classifier: Topic :: Utilities
Requires-Dist: pytest (>=6.2.4,<7.0.0)
